mmdzanata/__init__.py
mmdzanata/cli.py
mmdzanata/fedora.py
mmdzanata/fedora/__init__.py
mmdzanata-0.7.dist-info/METADATA
mmdzanata-0.7.dist-info/RECORD
mmdzanata-0.7.dist-info/WHEEL
mmdzanata-0.7.dist-info/entry_points.txt
mmdzanata-0.7.dist-info/top_level.txt
