Metadata-Version: 2.1
Name: mmdzanata
Version: 0.7
Summary: Tools for working with translations of modulemd
Home-page: https://github.com/sgallagher/modulemd-zanata
Author: Stephen Gallagher
Author-email: sgallagh@redhat.com
License: MIT
Platform: UNKNOWN
Classifier: Programming Language :: Python :: 3
Classifier: License :: OSI Approved :: MIT License
Classifier: Operating System :: POSIX :: Linux
Requires-Dist: click
Requires-Dist: requests
Requires-Dist: babel
